ByConfig/__init__.py
ByConfig/cli.py
ByConfig/py.typed
byconfig-0.1.0.dist-info/METADATA
byconfig-0.1.0.dist-info/WHEEL
byconfig-0.1.0.dist-info/entry_points.txt
byconfig-0.1.0.dist-info/top_level.txt
byconfig-0.1.0.dist-info/RECORD
